main.py
gigachain_upstage-100.0.1.dist-info/METADATA
gigachain_upstage-100.0.1.dist-info/WHEEL
gigachain_upstage-100.0.1.dist-info/top_level.txt
gigachain_upstage-100.0.1.dist-info/RECORD
