Metadata-Version: 2.4
Name: gigachain-upstage
Version: 100.0.1
Summary: Gigachain libs was deprectaed. Upgrade to clear langchain + langchain_gigachat
Requires-Python: >=3.12
